framework_api_key/__init__.py
framework_api_key/__version__.py
framework_api_key/admin.py
framework_api_key/apps.py
framework_api_key/crypto.py
framework_api_key/models.py
framework_api_key/permissions.py
framework_api_key/py.typed
framework_api_key/__pycache__/__init__.cpython-39.pyc
framework_api_key/__pycache__/__version__.cpython-39.pyc
framework_api_key/__pycache__/admin.cpython-39.pyc
framework_api_key/__pycache__/apps.cpython-39.pyc
framework_api_key/__pycache__/crypto.cpython-39.pyc
framework_api_key/__pycache__/models.cpython-39.pyc
framework_api_key/__pycache__/permissions.cpython-39.pyc
framework_api_key/migrations/0001_initial.py
framework_api_key/migrations/__init__.py
framework_api_key/migrations/__pycache__/0001_initial.cpython-39.pyc
framework_api_key/migrations/__pycache__/__init__.cpython-39.pyc
framework_api_key-0.0.1.dist-info/LICENSE
framework_api_key-0.0.1.dist-info/METADATA
framework_api_key-0.0.1.dist-info/WHEEL
framework_api_key-0.0.1.dist-info/top_level.txt
framework_api_key-0.0.1.dist-info/RECORD
